version_handle/__init__.py
version_handle/__version__.py
version_handle/entities.py
version_handle/generate.py
version_handle/python.py
version_handle-0.1.3.dist-info/LICENSE
version_handle-0.1.3.dist-info/METADATA
version_handle-0.1.3.dist-info/WHEEL
version_handle-0.1.3.dist-info/top_level.txt
version_handle-0.1.3.dist-info/RECORD
